{
  "generated_at": "2026-06-17T00:03:43.361561Z",
  "matches": [
    {
      "home": "France",
      "away": "Senegal",
      "score": "3-1",
      "utcDate": "2026-06-16T19:00:00Z"
    },
    {
      "home": "Saudi Arabia",
      "away": "Uruguay",
      "score": "1-1",
      "utcDate": "2026-06-15T22:00:00Z"
    },
    {
      "home": "Belgium",
      "away": "Egypt",
      "score": "1-1",
      "utcDate": "2026-06-15T19:00:00Z"
    },
    {
      "home": "Spain",
      "away": "Cape Verde Islands",
      "score": "0-0",
      "utcDate": "2026-06-15T16:00:00Z"
    }
  ]
}