{
  "generated_at": "2026-06-24T05:46:21.643659Z",
  "matches": [
    {
      "home": "Colombia",
      "away": "Congo DR",
      "score": "1-0",
      "utcDate": "2026-06-24T02:00:00Z"
    },
    {
      "home": "Panama",
      "away": "Croatia",
      "score": "0-1",
      "utcDate": "2026-06-23T23:00:00Z"
    },
    {
      "home": "England",
      "away": "Ghana",
      "score": "0-0",
      "utcDate": "2026-06-23T20:00:00Z"
    },
    {
      "home": "Portugal",
      "away": "Uzbekistan",
      "score": "5-0",
      "utcDate": "2026-06-23T17:00:00Z"
    },
    {
      "home": "Norway",
      "away": "Senegal",
      "score": "3-2",
      "utcDate": "2026-06-23T00:00:00Z"
    }
  ]
}